README.md
setup.py
slacknotify/__init__.py
slacknotify/tokenhandler.py
slacknotify.egg-info/PKG-INFO
slacknotify.egg-info/SOURCES.txt
slacknotify.egg-info/dependency_links.txt
slacknotify.egg-info/not-zip-safe
slacknotify.egg-info/requires.txt
slacknotify.egg-info/top_level.txt