Metadata-Version: 1.0
Name: slacknotify
Version: 0.1
Summary: Send notifications to slack from python
Home-page: https://github.com/Darel13712/slacknotify
Author: Darel
Author-email: darel142857@gmail.com
License: MIT
Platform: UNKNOWN
